README.rst
setup.py
colibri/__init__.py
colibri/_version.py
colibri/channel.py
colibri/connection.py
colibri/exceptions.py
colibri/frame.py
colibri/heartbeat.py
colibri/log.py
colibri/message.py
colibri/protocol.py
colibri/serialization.py
colibri/spec.py
colibri/utils.py
colibri.egg-info/PKG-INFO
colibri.egg-info/SOURCES.txt
colibri.egg-info/dependency_links.txt
colibri.egg-info/not-zip-safe
colibri.egg-info/requires.txt
colibri.egg-info/top_level.txt