Metadata-Version: 1.1
Name: colibri
Version: 0.0.1
Summary: asyncio-based implementation of AMQP client
Home-page: http://pypi.python.org/pypi/colibri
Author: Dmitry Malinovsky
Author-email: ['__contact__']
License: MIT
Keywords: colibri AMQP client asyncio
Platform: UNKNOWN
Classifier: Development Status :: 2 - Pre-Alpha
Classifier: Intended Audience :: Developers
Classifier: Intended Audience :: Information Technology
Classifier: License :: OSI Approved :: MIT License
Classifier: Operating System :: OS Independent
Classifier: Programming Language :: Python :: 3.3
Classifier: Programming Language :: Python :: 3.4
Classifier: Programming Language :: Python :: Implementation :: CPython
Classifier: Programming Language :: Python :: Implementation :: PyPy
